quant_analytics_flow/__init__.py
quant_analytics_flow/analytics/__init__.py
quant_analytics_flow/analytics/constants.py
quant_analytics_flow/analytics/matrixanalytics.py
quant_analytics_flow/analytics/maxsoft.py
quant_analytics_flow/analytics/norminv.py
quant_analytics_flow/calculators/__init__.py
quant_analytics_flow/calculators/multivariatebrownianbridge.py
quant_analytics_flow/calculators/univariatebrownianbridge.py
quant_analytics_flow-0.0.1.dist-info/LICENSE
quant_analytics_flow-0.0.1.dist-info/METADATA
quant_analytics_flow-0.0.1.dist-info/WHEEL
quant_analytics_flow-0.0.1.dist-info/top_level.txt
quant_analytics_flow-0.0.1.dist-info/RECORD
