Metadata-Version: 2.1
Name: quant-analytics-flow
Version: 0.0.1
Summary: Quantitative analytics package based on Tensorflow for deep learning of derivative pricing
Home-page: UNKNOWN
Author: UNKNOWN
Author-email: quant.analytics.torch@gmail.com
License: MIT License
Platform: UNKNOWN
